vyzeai/__init__.py
vyzeai/agents/__init__.py
vyzeai/agents/base_agent.py
vyzeai/agents/prebuilt_agents.py
vyzeai/agents/prebuilt_agents0.py
vyzeai/agents/react_agent.py
vyzeai/memory/__init__.py
vyzeai/memory/basic_memory.py
vyzeai/models/__init__.py
vyzeai/models/openai.py
vyzeai/prompts/__init__.py
vyzeai/prompts/react_prompt.py
vyzeai/tools/__init__.py
vyzeai/tools/base_tool.py
vyzeai/tools/prebuilt_tools.py
vyzeai/tools/python_repl.py
vyzeai/tools/raw_functions.py
vyzeai-0.1.15.dist-info/METADATA
vyzeai-0.1.15.dist-info/WHEEL
vyzeai-0.1.15.dist-info/top_level.txt
vyzeai-0.1.15.dist-info/RECORD
