Metadata-Version: 2.1
Name: vyzeai
Version: 0.1.15
Summary: A python package for generative ai
Home-page: https://github.com/prudvireddyNS/vyzeai
Author: Prudvi
Author-email: prudhvisneha2003@gmail.com
License: MIT
Classifier: License :: OSI Approved :: MIT License
Classifier: Programming Language :: Python :: 3.10
Classifier: Operating System :: OS Independent
Requires-Python: >=3.10
Requires-Dist: openai
Requires-Dist: requests
Requires-Dist: numpy
Requires-Dist: pydantic[email]
Provides-Extra: dev
Requires-Dist: pytest >=7.0 ; extra == 'dev'
Requires-Dist: twine >=4.0.2 ; extra == 'dev'
